poetry_first_project/__init__.py
poetry_first_project/main.py
poetry_first_project-0.1.0.dist-info/METADATA
poetry_first_project-0.1.0.dist-info/WHEEL
poetry_first_project-0.1.0.dist-info/RECORD
