Metadata-Version: 2.1
Name: poetry-first-project
Version: 0.1.0
Summary: 
Author: Abu Huraira
Author-email: huraira5314@gmail.com
Requires-Python: >=3.12,<4.0
Classifier: Programming Language :: Python :: 3
Classifier: Programming Language :: Python :: 3.12
Requires-Dist: pytest (>=8.1.2,<9.0.0)
